plain/jobs/CHANGELOG.md
plain/jobs/README.md
plain/jobs/__init__.py
plain/jobs/admin.py
plain/jobs/chores.py
plain/jobs/cli.py
plain/jobs/config.py
plain/jobs/default_settings.py
plain/jobs/exceptions.py
plain/jobs/jobs.py
plain/jobs/locks.py
plain/jobs/middleware.py
plain/jobs/models.py
plain/jobs/parameters.py
plain/jobs/registry.py
plain/jobs/scheduling.py
plain/jobs/workers.py
plain/jobs/migrations/0001_initial.py
plain/jobs/migrations/0002_job_span_id_job_trace_id_jobrequest_span_id_and_more.py
plain/jobs/migrations/0003_rename_job_jobprocess_and_more.py
plain/jobs/migrations/0004_rename_tables_to_plainjobs.py
plain/jobs/migrations/0005_rename_constraints_and_indexes.py
plain/jobs/migrations/0006_alter_jobprocess_table_alter_jobrequest_table_and_more.py
plain/jobs/migrations/0007_remove_jobrequest_plainjobs_jobrequest_unique_job_class_key_and_more.py
plain/jobs/migrations/__init__.py
plain/jobs/templates/admin/plainqueue/jobresult_detail.html
plain_jobs-0.42.0.dist-info/METADATA
plain_jobs-0.42.0.dist-info/WHEEL
plain_jobs-0.42.0.dist-info/licenses/LICENSE
plain_jobs-0.42.0.dist-info/RECORD
